stlog/__init__.py
stlog/adapter.py
stlog/base.py
stlog/context.py
stlog/filter.py
stlog/formatter.py
stlog/handler.py
stlog/kvformatter.py
stlog/output.py
stlog/py.typed
stlog/setup.py
stlog-0.5.0.dist-info/METADATA
stlog-0.5.0.dist-info/WHEEL
stlog-0.5.0.dist-info/licenses/LICENSE
stlog-0.5.0.dist-info/RECORD
