Metadata-Version: 2.4
Name: stlog
Version: 0.5.0
Summary: Dependency free structured logging library fully compatible with standard Python logging with "good/opinionated" default values
Project-URL: Homepage, https://github.com/fabien-marty/stlog
Project-URL: Documentation, https://fabien-marty.github.io/stlog/
Project-URL: Repository, https://github.com/fabien-marty/stlog.git
Author-email: Fabien MARTY <fabien.marty@gmail.com>
Maintainer-email: Fabien MARTY <fab@fabien-marty.dev>
License-Expression: MIT
License-File: LICENSE
Keywords: logging,structured
Classifier: Development Status :: 4 - Beta
Classifier: License :: OSI Approved :: MIT License
Classifier: Programming Language :: Python :: 3 :: Only
Classifier: Topic :: System :: Logging
Requires-Python: >=3.7
